fei_crypto/__init__.py
fei_crypto/binance_signal.py
fei_crypto/captcha.py
fei_crypto/crypto.py
fei_crypto/discord_webhook.py
fei_crypto/env.py
fei_crypto/md5.py
fei_crypto/os_info.py
fei_crypto/rmw.py
fei_crypto/rnd_emoj.py
fei_crypto/t2m.py
fei_crypto/time.py
main/__init__.py
main/binance_signal.py
main/btc_eth.py
main/captcha.py
main/dc_webhook_send.py
main/emoj.py
main/env.py
main/main.py
main/os_info.py
main/rmw.py
main/say.py
main/t2m.py
main/tg_forward.py
main/tg_koltime_menu.py
main/tg_login.py
main/ts.py
main/uu_id.py
tests/__init__.py
tests/calc.py
tests/console.py
tests/dict.py
tests/enum_test.py
tests/env_test.py
tests/format_test.py
tests/getattr.py
tests/hello.py
tests/image_base64.py
tests/logging_test.py
tests/manim.py
tests/open.py
tests/path.py
tests/redis_hash.py
tests/redis_json.py
tests/redis_json_ticker_price.py
tests/redis_koltime_channels.py
tests/redis_set_test.py
tests/scope_test.py
tests/str_test.py
tests/tg_arbitrarycallbackdatabot.py
tests/tg_inlinebot.py
tests/tg_inlinekeyboard.py
tests/tg_inlinekeyboard2.py
tests/tg_nestedconversationbot.py
tests/tg_pollbot.py
tests/tg_rawapibot.py
tests/tg_webappbot.py
tests/time_test.py
tests/tuple.py
tests/tuple_list.py
tests/typer.py
tg/__init__.py
tg/bot/__init__.py
tg/bot/live_bot.py
tg/bot/utils.py
tg/cli_forward.py
tg/cli_login.py
tg/config.py
tg/const.py
tg/koltime_menu_bot.py
tg/koltime_menu_bot1.py
tg/live.py
tg/login.py
tg/message.py
tg/parse.py
tg/past.py
tg/plugin_models.py
tg/plugins/__init__.py
tg/plugins/caption.py
tg/plugins/filter.py
tg/plugins/fmt.py
tg/plugins/replace.py
tg/storage.py
tg/utils.py
fei_crypto-0.2.8.dist-info/entry_points.txt
fei_crypto-0.2.8.dist-info/LICENSE
fei_crypto-0.2.8.dist-info/METADATA
fei_crypto-0.2.8.dist-info/WHEEL
fei_crypto-0.2.8.dist-info/RECORD
