Metadata-Version: 2.1
Name: fei-crypto
Version: 0.2.8
Summary: fei crypto command utils
License: MIT
Author: feicrypto
Author-email: feicrypto@proton.me
Requires-Python: >=3.10,<3.12
Classifier: License :: OSI Approved :: MIT License
Classifier: Programming Language :: Python :: 3
Classifier: Programming Language :: Python :: 3.10
Classifier: Programming Language :: Python :: 3.11
Requires-Dist: cowsay (>=6.1,<7.0)
Requires-Dist: discord-webhook (>=1.3.1,<2.0.0)
Requires-Dist: filestools (>=0.2.1,<0.3.0)
Requires-Dist: ipython (>=8.23.0,<9.0.0)
Requires-Dist: manim (>=0.18.0,<0.19.0)
Requires-Dist: pillow (>=9.5.0,<10.0.0)
Requires-Dist: pymongo (>=4.6.3,<5.0.0)
Requires-Dist: pymysql (>=1.1.0,<2.0.0)
Requires-Dist: python-dotenv (>=1.0.0,<2.0.0)
Requires-Dist: python-socks[asyncio] (>=2.4.3,<3.0.0)
Requires-Dist: python-telegram-bot[callback-data,socks] (>=21.1,<22.0)
Requires-Dist: pyyaml (>=6.0.1,<7.0.0)
Requires-Dist: redis (>=5.0.3,<6.0.0)
Requires-Dist: requests[socks] (>=2.31.0,<3.0.0)
Requires-Dist: rich (>=13.7.1,<14.0.0)
Requires-Dist: telethon (>=1.34.0,<2.0.0)
Requires-Dist: typer[all] (>=0.9.0,<0.10.0)
Requires-Dist: verlat (>=0.1.0.post1,<0.2.0)
